krithik_dclab/__init__.py
krithik_dclab/cli.py
krithik_dclab/data/exp1_LoadBalancing/LoadBalancers.java
krithik_dclab/data/exp2_Multithreading/Multithreadings.java
krithik_dclab/data/exp3_RPC/Client.java
krithik_dclab/data/exp3_RPC/Server.java
krithik_dclab/data/exp4_BullyElection/BullyAlgo.java
krithik_dclab/data/exp5_GroupCommunication/Master.java
krithik_dclab/data/exp5_GroupCommunication/Server.java
krithik_dclab/data/exp5_GroupCommunication/Slave1.java
krithik_dclab/data/exp5_GroupCommunication/Slave2.java
krithik_dclab/data/exp6_ChandyHaasMisra/ChandyHaasMisra.java
krithik_dclab/data/exp7_IPC/IPCClient.java
krithik_dclab/data/exp7_IPC/IPCServer.java
krithik_dclab/data/exp8_MutualExclusion/ClientOne.java
krithik_dclab/data/exp8_MutualExclusion/ClientTwo.java
krithik_dclab/data/exp8_MutualExclusion/MutualServer.java
krithik_dclab/data/exp9_BerkleyClockSync/Berkley.java
krithik_dclab/data/lab_assign_exp1_LoadBalancing/LoadBalancers.java
krithik_dclab/data/lab_assign_exp3_RPC/Client.java
krithik_dclab/data/lab_assign_exp3_RPC/Server.java
krithik_dclab/data/lab_assign_exp4_RingElection/RingAlgo.java
krithik_dclab/data/lab_assign_exp6_PathPushing/PathPushing.java
krithik_dclab-0.1.2.dist-info/LICENSE
krithik_dclab-0.1.2.dist-info/METADATA
krithik_dclab-0.1.2.dist-info/WHEEL
krithik_dclab-0.1.2.dist-info/entry_points.txt
krithik_dclab-0.1.2.dist-info/top_level.txt
krithik_dclab-0.1.2.dist-info/RECORD
