Metadata-Version: 2.1
Name: krithik-dclab
Version: 0.1.2
Summary: A package to print Java source code from Distributed Computing Lab experiments
Home-page: https://github.com/yourusername/krithik-dclab
Author: Krithik Patil
Author-email: your.email@example.com
License: MIT
Classifier: Programming Language :: Python :: 3
Classifier: License :: OSI Approved :: MIT License
Classifier: Operating System :: OS Independent
Requires-Python: >=3.6
License-File: LICENSE
Requires-Dist: click >=8.0
